biojson/__init__.py
biojson-0.1.0.dist-info/LICENSE.txt
biojson-0.1.0.dist-info/METADATA
biojson-0.1.0.dist-info/WHEEL
biojson-0.1.0.dist-info/entry_points.txt
biojson-0.1.0.dist-info/top_level.txt
biojson-0.1.0.dist-info/RECORD
