Metadata-Version: 2.1
Name: biojson
Version: 0.1.0
Summary: biojson
Home-page: https://github.com/ialbert/biojson-central
Author: Istvan Albert
Author-email: istvan.albert@gmail.com
Classifier: Programming Language :: Python :: 3
Classifier: License :: OSI Approved :: MIT License
Classifier: Operating System :: OS Independent
Requires-Python: >=3.8
License-File: LICENSE.txt
Requires-Dist: biopython
